lpc/__init__.py
lpc/cmd.py
lpc/main.py
lpc/parts.py
little_python_computer-0.2.3.dist-info/LICENSE
little_python_computer-0.2.3.dist-info/METADATA
little_python_computer-0.2.3.dist-info/WHEEL
little_python_computer-0.2.3.dist-info/entry_points.txt
little_python_computer-0.2.3.dist-info/top_level.txt
little_python_computer-0.2.3.dist-info/RECORD
