Metadata-Version: 2.1
Name: little-python-computer
Version: 0.2.3
Summary: Python implementation of the Little Man Computer with additional SFT instruction.
Author-email: Douglas Luman <dluman@allegheny.edu>
License-File: LICENSE
Requires-Dist: arglite
